aibrix_kvcache/__init__.py
aibrix_kvcache/_aibrix_C.abi3.so
aibrix_kvcache/_custom_ops.py
aibrix_kvcache/_version.py
aibrix_kvcache/cache_args.py
aibrix_kvcache/cache_handle.py
aibrix_kvcache/cache_hashable.py
aibrix_kvcache/cache_manager.py
aibrix_kvcache/config.py
aibrix_kvcache/envs.py
aibrix_kvcache/metrics.py
aibrix_kvcache/profiling.py
aibrix_kvcache/spec.py
aibrix_kvcache/status.py
aibrix_kvcache/utils.py
aibrix_kvcache/version.py
aibrix_kvcache/common/__init__.py
aibrix_kvcache/common/absl_logging.py
aibrix_kvcache/common/async_base.py
aibrix_kvcache/common/cached_pyobject.py
aibrix_kvcache/common/object_pool.py
aibrix_kvcache/common/threading.py
aibrix_kvcache/l1/__init__.py
aibrix_kvcache/l1/l1_cache.py
aibrix_kvcache/l1/eviction_policy/__init__.py
aibrix_kvcache/l1/eviction_policy/base_eviction_policy.py
aibrix_kvcache/l1/eviction_policy/fifo.py
aibrix_kvcache/l1/eviction_policy/lru.py
aibrix_kvcache/l1/eviction_policy/s3fifo.py
aibrix_kvcache/l2/__init__.py
aibrix_kvcache/l2/l2_cache.py
aibrix_kvcache/l2/connectors/__init__.py
aibrix_kvcache/l2/connectors/connector.py
aibrix_kvcache/l2/connectors/hpkv.py
aibrix_kvcache/l2/connectors/infinistore.py
aibrix_kvcache/l2/connectors/mock.py
aibrix_kvcache/l2/connectors/pris.py
aibrix_kvcache/l2/connectors/rocksdb.py
aibrix_kvcache/l2/connectors/eic/README.md
aibrix_kvcache/l2/connectors/eic/__init__.py
aibrix_kvcache/l2/connectors/eic/eic.py
aibrix_kvcache/l2/connectors/eic/test_eic.py
aibrix_kvcache/l2/key_builders/__init__.py
aibrix_kvcache/l2/key_builders/hasher.py
aibrix_kvcache/l2/key_builders/hex_key_builder.py
aibrix_kvcache/l2/key_builders/key_builder.py
aibrix_kvcache/l2/key_builders/raw_key_builder.py
aibrix_kvcache/l2/key_builders/rolling_hash_key_builder.py
aibrix_kvcache/l2/key_builders/simple_hash_key_builder.py
aibrix_kvcache/l2/marshallers/__init__.py
aibrix_kvcache/l2/marshallers/marshaller.py
aibrix_kvcache-0.5.0.dist-info/METADATA
aibrix_kvcache-0.5.0.dist-info/WHEEL
aibrix_kvcache-0.5.0.dist-info/top_level.txt
aibrix_kvcache-0.5.0.dist-info/RECORD
aibrix_kvcache-0.5.0.dist-info/licenses/LICENSE
