Metadata-Version: 2.4
Name: aibrix-kvcache
Version: 0.5.0
Summary: AIBrix KV Cache offloading framework for cross-engine KV reuse
Author: AIBrix Team
License-Expression: Apache-2.0
Classifier: Programming Language :: Python :: 3.11
Classifier: Programming Language :: Python :: 3.12
Classifier: Intended Audience :: Developers
Classifier: Intended Audience :: Information Technology
Classifier: Intended Audience :: Science/Research
Classifier: Topic :: Scientific/Engineering :: Artificial Intelligence
Classifier: Topic :: Scientific/Engineering :: Information Analysis
License-File: LICENSE
Requires-Dist: asyncio>=3.4.3
Requires-Dist: cityhash>=0.4.8
Requires-Dist: more-itertools>=10.7.0
Requires-Dist: msgspec>=0.19.0
Requires-Dist: netifaces
Requires-Dist: numpy>=1.26.4
Requires-Dist: requests>=2.26.0
Requires-Dist: tqdm>=4.67.1
Requires-Dist: pydantic>=2.10
Requires-Dist: pyyaml
Requires-Dist: setuptools<80,>=77.0.3; python_version > "3.11"
Requires-Dist: sortedcontainers>=2.4.0
Requires-Dist: uvloop
Requires-Dist: validators>=0.35.0
Requires-Dist: zstandard
Requires-Dist: redis>=6.0.0
Requires-Dist: nvtx
Requires-Dist: torch>=2.7.0
Requires-Dist: pyroscope-io
Requires-Dist: rocksdict
Dynamic: license-file
Dynamic: requires-dist
